{"metadata": {"dbt_schema_version": "https://schemas.getdbt.com/dbt/run-results/v6.json", "dbt_version": "1.8.4", "generated_at": "2026-06-18T21:04:42.196391Z", "invocation_id": "1f047f39-8251-4872-a744-a91bbc5fb9ff", "env": {}}, "results": [{"status": "success", "timing": [{"name": "compile", "started_at": "2026-06-18T21:04:41.979707Z", "completed_at": "2026-06-18T21:04:41.992849Z"}, {"name": "execute", "started_at": "2026-06-18T21:04:41.993622Z", "completed_at": "2026-06-18T21:04:42.158868Z"}], "thread_id": "Thread-1 (worker)", "execution_time": 0.19011735916137695, "adapter_response": {"_message": "OK"}, "message": "OK", "failures": null, "unique_id": "model.dbt_chess.stg_lichess_games", "compiled": true, "compiled_code": "-- =============================================================================\n-- stg_lichess_games\n-- Bronze Layer \u2014 Partidas Lichess.org\n--\n-- L\u00ea os arquivos Parquet da Bronze Layer via DuckDB e aplica:\n--   - Valida\u00e7\u00e3o de campos obrigat\u00f3rios\n--   - Cast expl\u00edcito de tipos\n--   - Normaliza\u00e7\u00e3o de campos aninhados do ND-JSON (players, clock)\n--   - Padroniza\u00e7\u00e3o de colunas para modelo can\u00f4nico\n-- =============================================================================\n\n\n\nWITH source AS (\n    SELECT *\n    FROM read_parquet(\n        '/opt/airflow/data/bronze/lichess/**/*.parquet',\n        union_by_name = true\n    )\n),\n\nvalidated AS (\n    SELECT\n        -- Identifica\u00e7\u00e3o\n        CAST(game_id        AS VARCHAR)     AS game_id,\n\n        -- Metadados do jogo\n        CAST(variant        AS VARCHAR)     AS variant,\n        CAST(speed          AS VARCHAR)     AS speed,\n        CAST(perf           AS VARCHAR)     AS perf,\n        CAST(status         AS VARCHAR)     AS status,\n\n        -- Temporal\n        CAST(created_at     AS TIMESTAMPTZ) AS created_at,\n        CAST(last_move_at   AS TIMESTAMPTZ) AS last_move_at,\n\n        -- Metadado de ingest\u00e3o\n        CAST(ingestion_ts   AS TIMESTAMPTZ) AS ingestion_ts,\n\n        -- Flags\n        CAST(rated          AS BOOLEAN)     AS is_rated,\n\n        -- Jogador Branco\n        LOWER(CAST(white_id     AS VARCHAR)) AS white_id,\n        CAST(white_rating       AS INTEGER)  AS white_rating,\n        CAST(white_result       AS VARCHAR)  AS white_result,\n\n        -- Jogador Preto\n        LOWER(CAST(black_id     AS VARCHAR)) AS black_id,\n        CAST(black_rating       AS INTEGER)  AS black_rating,\n        CAST(black_result       AS VARCHAR)  AS black_result,\n\n        -- Movimentos\n        CAST(moves          AS VARCHAR)     AS moves,\n\n        -- Rel\u00f3gio\n        CAST(clock_initial  AS INTEGER)     AS clock_initial_secs,\n        CAST(clock_increment AS INTEGER)    AS clock_increment_secs,\n\n        -- Dura\u00e7\u00e3o total da partida em segundos\n        CASE\n            WHEN last_move_at IS NOT NULL AND created_at IS NOT NULL\n            THEN EPOCH(CAST(last_move_at AS TIMESTAMPTZ)) -\n                 EPOCH(CAST(created_at   AS TIMESTAMPTZ))\n            ELSE NULL\n        END AS game_duration_secs\n\n    FROM source\n\n    -- Filtro de qualidade: game_id obrigat\u00f3rio\n    WHERE game_id IS NOT NULL\n    \n      AND created_at >= '2026-06-11'::timestamptz\n      AND created_at < ('2026-06-18'::timestamptz + interval '1 day')\n    \n),\n\ndeduped AS (\n    SELECT *,\n        ROW_NUMBER() OVER (\n            PARTITION BY game_id\n            ORDER BY ingestion_ts DESC\n        ) AS row_num\n    FROM validated\n)\n\nSELECT\n    game_id,\n    variant,\n    speed,\n    perf,\n    status,\n    created_at,\n    last_move_at,\n    game_duration_secs,\n    ingestion_ts,\n    is_rated,\n    white_id,\n    white_rating,\n    white_result,\n    black_id,\n    black_rating,\n    black_result,\n    moves,\n    clock_initial_secs,\n    clock_increment_secs\n\nFROM deduped\nWHERE row_num = 1", "relation_name": "\"chess\".\"bronze_bronze\".\"stg_lichess_games\""}], "elapsed_time": 0.38637375831604004, "args": {"cache_selected_only": false, "warn_error_options": {"include": [], "exclude": []}, "require_explicit_package_overrides_for_builtin_materializations": true, "defer": false, "use_colors": true, "invocation_command": "dbt run --select bronze.stg_lichess_games --project-dir /opt/airflow/dbt_chess --profiles-dir /opt/airflow/dbt_chess --vars {\"start_date\": \"2026-06-11\", \"end_date\": \"2026-06-18\"}", "vars": {"start_date": "2026-06-11", "end_date": "2026-06-18"}, "partial_parse_file_diff": true, "show_resource_report": false, "printer_width": 80, "indirect_selection": "eager", "version_check": true, "send_anonymous_usage_stats": true, "log_file_max_bytes": 10485760, "project_dir": "/opt/airflow/dbt_chess", "profiles_dir": "/opt/airflow/dbt_chess", "log_format_file": "debug", "write_json": true, "log_format": "default", "require_resource_names_without_spaces": false, "populate_cache": true, "macro_debugging": false, "quiet": false, "empty": false, "introspect": true, "print": true, "favor_state": false, "enable_legacy_logger": false, "source_freshness_run_project_hooks": false, "partial_parse": true, "select": ["bronze.stg_lichess_games"], "strict_mode": false, "exclude": [], "use_colors_file": true, "static_parser": true, "which": "run", "log_path": "/opt/airflow/dbt_chess/logs", "log_level_file": "debug", "log_level": "info"}}